{
  "name": "stats",
  "title": "stats",
  "description": "A simple stats block",
  "category": "yellow-peach",
  "icon": "chart-pie",
  "keywords": [
    "numbers",
    "USP",
    "points"
  ],
  "acf": {
    "mode": "auto",
    "validate": false
  },
  "supports": {
    "align": false,
    "anchor": true,
    "alignContent": false,
    "color": {
      "text": false,
      "background": true,
      "link": true
    },
    "alignText": true,
    "spacing": {
      "margin": false,
      "padding": true
    }
  }
}
